pytest_yaml_fei
